langevals_openai/moderation.py
langevals_openai-0.1.13.dist-info/METADATA
langevals_openai-0.1.13.dist-info/WHEEL
langevals_openai-0.1.13.dist-info/RECORD
