Metadata-Version: 2.4
Name: langevals-openai
Version: 0.1.13
Summary: LangEvals OpenAI moderation evaluator for LLM outputs.
License: MIT
Author: Rogerio Chaves
Author-email: rogerio@langwatch.ai
Requires-Python: >=3.11,<4.0
Classifier: License :: OSI Approved :: MIT License
Classifier: Programming Language :: Python :: 3
Classifier: Programming Language :: Python :: 3.11
Classifier: Programming Language :: Python :: 3.12
Classifier: Programming Language :: Python :: 3.13
Classifier: Programming Language :: Python :: 3.14
Requires-Dist: langevals-core (>=0.1.18,<0.2.0)
Requires-Dist: openai (>=1.27.0)
Requires-Dist: tqdm (>=4.66.4,<5.0.0)
